.gitignore
CONTRIBUTORS.md
GOOSE-LICENSE.txt
LICENSE
MANIFEST.in
README.rst
download_corpora.py
requirements.txt
setup.py
newspaper/__init__.py
newspaper/api.py
newspaper/article.py
newspaper/cleaners.py
newspaper/configuration.py
newspaper/extractors.py
newspaper/images.py
newspaper/mthreading.py
newspaper/network.py
newspaper/nlp.py
newspaper/outputformatters.py
newspaper/parsers.py
newspaper/settings.py
newspaper/source.py
newspaper/text.py
newspaper/urls.py
newspaper/utils.py
newspaper/version.py
newspaper.egg-info/PKG-INFO
newspaper.egg-info/SOURCES.txt
newspaper.egg-info/dependency_links.txt
newspaper.egg-info/not-zip-safe
newspaper.egg-info/requires.txt
newspaper.egg-info/top_level.txt