Metadata-Version: 1.0
Name: newspaper
Version: 0.1.0.3
Summary: Simplified python article discovery & extraction.
Home-page: https://github.com/codelucas/newspaper/
Author: Lucas Ou-Yang
Author-email: lucasyangpersonal@gmail.com
License: MIT
Platform: UNKNOWN
